RLIB/__init__.py
RLIB/ai_core.py
rosha_rlib-0.1.1.dist-info/METADATA
rosha_rlib-0.1.1.dist-info/WHEEL
rosha_rlib-0.1.1.dist-info/top_level.txt
rosha_rlib-0.1.1.dist-info/RECORD
