Metadata-Version: 2.4
Name: rosha_RLIB
Version: 0.1.1
Summary: A simple AI helper library for generating responses, summarizing text, and formatting output.
Author: Rosha Thankachan 
Author-email: roshathankachan459@gmail.com
Classifier: Programming Language :: Python :: 3
Classifier: License :: OSI Approved :: MIT License
Classifier: Operating System :: OS Independent
Requires-Python: >=3.7
Requires-Dist: openai
Requires-Dist: requests
Dynamic: author
Dynamic: author-email
Dynamic: classifier
Dynamic: description
Dynamic: description-content-type
Dynamic: requires-dist
Dynamic: requires-python
Dynamic: summary
